inertialsense_math/__init__.py
inertialsense_math/pose.py
inertialsense_math-0.0.5.dist-info/LICENSE
inertialsense_math-0.0.5.dist-info/METADATA
inertialsense_math-0.0.5.dist-info/WHEEL
inertialsense_math-0.0.5.dist-info/top_level.txt
inertialsense_math-0.0.5.dist-info/RECORD
