Metadata-Version: 2.1
Name: inertialsense-math
Version: 0.0.5
Summary: Inertial Sense Math Functions
Home-page: https://github.com/inertialsense/inertial-sense-sdk
Author: Inertial Sense Build Bot
Author-email: steven+pypi.org@inertialsense.com
License: UNKNOWN
Project-URL: Bug Tracker, https://github.com/inertialsense/inertial-sense-sdk/issues
Platform: UNKNOWN
Classifier: Programming Language :: Python
Classifier: License :: OSI Approved :: MIT License
Classifier: Operating System :: OS Independent
Requires-Python: >=2.7
